eismultiplexer/__init__.py
eismultiplexer/_core.cpython-313-x86_64-linux-gnu.so
eismultiplexer.libs/libblkid-a9167753.so.1.1.0
eismultiplexer.libs/libmount-ec61bd71.so.1.1.0
eismultiplexer.libs/libpcre2-8-516f4c9d.so.0.7.1
eismultiplexer.libs/libselinux-d0805dcb.so.1
eismultiplexer.libs/libudev-9765ffbd.so.1.6.11
eismultiplexer.libs/libusb-1-1b307d35.0.so.0.2.0
eismultiplexer.libs/libuuid-95b83d40.so.1.3.0
eismultiplexer-1.6.2.dist-info/METADATA
eismultiplexer-1.6.2.dist-info/WHEEL
eismultiplexer-1.6.2.dist-info/top_level.txt
eismultiplexer-1.6.2.dist-info/RECORD
eismultiplexer-1.6.2.dist-info/licenses/LICENSE
