Metadata-Version: 2.4
Name: eismultiplexer
Version: 1.6.2
Author: Carl Philipp Klemm
License-Expression: LGPL-2.0-or-later
Requires-Python: >=3.8
License-File: LICENSE
Requires-Dist: libusb-package
Dynamic: author
Dynamic: license-file
Dynamic: requires-python
